timeframe/__init__.py
timeframe/timeframe.py
timeframe-3.0.3.dist-info/licenses/LICENSE
timeframe-3.0.3.dist-info/METADATA
timeframe-3.0.3.dist-info/WHEEL
timeframe-3.0.3.dist-info/top_level.txt
timeframe-3.0.3.dist-info/RECORD
